merabet/__init__.py
merabet-0.7.dist-info/LICENSE.txt
merabet-0.7.dist-info/METADATA
merabet-0.7.dist-info/WHEEL
merabet-0.7.dist-info/top_level.txt
merabet-0.7.dist-info/RECORD
